byid/__init__.py
byid/utils.py
byid/doi/__init__.py
byid/doi/__main__.py
byid/doi/service.py
byid-2021.5.8.dist-info/LICENSE
byid-2021.5.8.dist-info/METADATA
byid-2021.5.8.dist-info/WHEEL
byid-2021.5.8.dist-info/entry_points.txt
byid-2021.5.8.dist-info/top_level.txt
byid-2021.5.8.dist-info/RECORD
